Metadata-Version: 1.2
Name: fast-trace
Version: 3.1.30
Summary: FAST Python Agent
Home-page: http://doc.mypaas.com.cn/fast/03_%E6%9C%8D%E5%8A%A1%E7%AB%AF%E6%8E%A2%E9%92%88%E9%9B%86%E6%88%90/%E7%AE%80%E4%BB%8B.html
Author: FAST
Author-email: yangzy02@mingyuanyun.com
License: Apache-2.0
Platform: UNKNOWN
Requires-Python: >=2.7,!=3.0.*,!=3.1.*,!=3.2.*,!=3.3.*,!=3.4.*
